zoomconnect_sdk/__init__.py
zoomconnect_sdk/_test.py
zoomconnect_sdk/base_client.py
zoomconnect_sdk/client.py
zoomconnect_sdk/error.py
zoomconnect_sdk-0.0.3.dist-info/LICENSE
zoomconnect_sdk-0.0.3.dist-info/METADATA
zoomconnect_sdk-0.0.3.dist-info/WHEEL
zoomconnect_sdk-0.0.3.dist-info/top_level.txt
zoomconnect_sdk-0.0.3.dist-info/RECORD
