Metadata-Version: 2.1
Name: zoomconnect-sdk
Version: 0.0.3
Summary: Python Wrapper module for ZoomConnect API
Home-page: https://github.com/Lambrie/zoomconnect_sdk
Author: LambrieSteyn
Author-email: lambrie45@gmail.com
License: UNKNOWN
Keywords: Zoom ZoomConnect SMS Messages
Platform: UNKNOWN
Classifier: Programming Language :: Python :: 3
Classifier: License :: OSI Approved :: MIT License
Classifier: Operating System :: OS Independent
Requires-Python: >=3.6
Requires-Dist: requests (>=2.18.4)
Requires-Dist: six (>=1.11.0)
